django_site_configs-0.4.0.dist-info/licenses/LICENSE.mit.txt
siteconfigs/__init__.py
siteconfigs/__version__.py
siteconfigs/admin.py
siteconfigs/apps.py
siteconfigs/config.py
siteconfigs/models.py
siteconfigs/tests.py
siteconfigs/urls.py
siteconfigs/views.py
siteconfigs/api/seriealizers.py
siteconfigs/api/urls.py
siteconfigs/api/views.py
siteconfigs/migrations/0001_initial.py
siteconfigs/migrations/0002_auto_20210818_2301.py
siteconfigs/migrations/0003_auto_20240923_1656.py
siteconfigs/migrations/__init__.py
django_site_configs-0.4.0.dist-info/METADATA
django_site_configs-0.4.0.dist-info/WHEEL
django_site_configs-0.4.0.dist-info/top_level.txt
django_site_configs-0.4.0.dist-info/RECORD
